molecule_multipass/__init__.py
molecule_multipass/driver.py
molecule_multipass/cookiecutter/cookiecutter.json
molecule_multipass/cookiecutter/{{cookiecutter.molecule_directory}}/{{cookiecutter.scenario_name}}/converge.yml
molecule_multipass/cookiecutter/{{cookiecutter.molecule_directory}}/{{cookiecutter.scenario_name}}/prepare.yml
molecule_multipass/playbooks/create.yml
molecule_multipass/playbooks/destroy.yml
molecule_multipass/playbooks/templates/cloud-init.yml.j2
molecule_multipass-0.5.0.dist-info/LICENSE
molecule_multipass-0.5.0.dist-info/METADATA
molecule_multipass-0.5.0.dist-info/WHEEL
molecule_multipass-0.5.0.dist-info/entry_points.txt
molecule_multipass-0.5.0.dist-info/top_level.txt
molecule_multipass-0.5.0.dist-info/RECORD
