Metadata-Version: 2.1
Name: molecule-multipass
Version: 0.5.0
Summary: Molecule Multipass
Author-email: Andrey Gubarev <andrey@andreygubarev.com>
License: MIT
Project-URL: Homepage, https://github.com/andreygubarev/molecule-multipass/
License-File: LICENSE
Requires-Dist: molecule (>=5.0)
